[

    {
        "user": 3,
        "event": {
        "type": "join",
        "time": 5200.520336786435,
        "content": null
        }
    },
    {
        "user": 3,
        "event": {
         "type": "request",
         "time": 63000.99017777419,
         "content": {
          "id": 1,
          "name": "video0",
          "seeder": 3,
          "seeder_region": "W",
          "popularity": 218
         }
        }
    },
    {
        "user": 3,
        "event": {
         "type": "leave",
         "time": 70000.68367164594,
         "content": null
        }
    }
]